{
  "id": "pop-writer-creative",
  "version": "4.4.0",
  "displayName": "创意打磨",
  "description": "创意打磨 v4.4.0。用户给模糊想法 → trope-library 查询 + 联网搜索生成 2-3 个故事概念选项 → 用户选择 → 产出 全书立项PRD.md（宪法结构10块）。网文基准2k-3k字/章。模板见 references/prd-模板-空白.md。",
  "pipeline": {
    "upstream": ["pop-decon"],
    "downstream": ["pop-writer-world", "pop-writer-plot"],
    "references": ["pop-trope-library"]
  },
  "entry": "SKILL.md",
  "activation": {
    "slashCommands": ["开书", "创意", "creative", "新书"],
    "default": false
  },
  "permissions": {
    "readProjectFiles": true,
    "writeProjectFiles": true,
    "network": true
  }
}
